{
  "EU": {
    "employment": {
      "11": 1565900,
      "12": 2751900,
      "13": 3366900,
      "14": 2402400,
      "21": 7276900,
      "22": 5864400,
      "23": 10782000,
      "24": 9283000,
      "25": 4920600,
      "26": 5872500,
      "31": 6908000,
      "32": 6176500,
      "33": 13130800,
      "34": 3580400,
      "35": 2055699,
      "41": 8357200,
      "42": 3523900,
      "43": 6011300,
      "44": 1601900,
      "51": 8758000,
      "52": 13535100,
      "53": 6433100,
      "54": 3121700,
      "61": 5052900,
      "62": 268100,
      "63": 13700,
      "71": 7598800,
      "72": 7320700,
      "73": 904600,
      "74": 3032700,
      "75": 3845300,
      "81": 4807800,
      "82": 1719400,
      "83": 8299400,
      "91": 6345000,
      "92": 1495600,
      "93": 5344100,
      "94": 1464300,
      "95": 93100,
      "96": 1871600,
      "01": 245800,
      "02": 339600,
      "03": 587900
    },
    "earnings": {
      "10": 23.11,
      "11": 23.11,
      "12": 23.11,
      "13": 23.11,
      "14": 23.11,
      "15": 23.11,
      "16": 23.11,
      "17": 23.11,
      "18": 23.11,
      "19": 23.11,
      "20": 19.6,
      "21": 19.6,
      "22": 19.6,
      "23": 19.6,
      "24": 19.6,
      "25": 19.6,
      "26": 19.6,
      "27": 19.6,
      "28": 19.6,
      "29": 19.6,
      "30": 16.5,
      "31": 16.5,
      "32": 16.5,
      "33": 16.5,
      "34": 16.5,
      "35": 16.5,
      "36": 16.5,
      "37": 16.5,
      "38": 16.5,
      "39": 16.5,
      "40": 12.78,
      "41": 12.78,
      "42": 12.78,
      "43": 12.78,
      "44": 12.78,
      "45": 12.78,
      "46": 12.78,
      "47": 12.78,
      "48": 12.78,
      "49": 12.78,
      "50": 10.04,
      "51": 10.04,
      "52": 10.04,
      "53": 10.04,
      "54": 10.04,
      "55": 10.04,
      "56": 10.04,
      "57": 10.04,
      "58": 10.04,
      "59": 10.04,
      "60": 12.16,
      "61": 12.16,
      "62": 12.16,
      "63": 12.16,
      "64": 12.16,
      "65": 12.16,
      "66": 12.16,
      "67": 12.16,
      "68": 12.16,
      "69": 12.16,
      "70": 12.06,
      "71": 12.06,
      "72": 12.06,
      "73": 12.06,
      "74": 12.06,
      "75": 12.06,
      "76": 12.06,
      "77": 12.06,
      "78": 12.06,
      "79": 12.06,
      "80": 10.81,
      "81": 10.81,
      "82": 10.81,
      "83": 10.81,
      "84": 10.81,
      "85": 10.81,
      "86": 10.81,
      "87": 10.81,
      "88": 10.81,
      "89": 10.81,
      "90": 8.81,
      "91": 8.81,
      "92": 8.81,
      "93": 8.81,
      "94": 8.81,
      "95": 8.81,
      "96": 8.81,
      "97": 8.81,
      "98": 8.81,
      "99": 8.81,
      "00": 17.6,
      "01": 17.6,
      "02": 17.6,
      "03": 17.6,
      "04": 17.6,
      "05": 17.6,
      "06": 17.6,
      "07": 17.6,
      "08": 17.6,
      "09": 17.6
    }
  },
  "AT": {
    "employment": {
      "11": 34400,
      "12": 87100,
      "13": 83000,
      "14": 36200,
      "21": 145000,
      "22": 185300,
      "23": 239100,
      "24": 142000,
      "25": 120800,
      "26": 132400,
      "31": 220000,
      "32": 75400,
      "33": 370500,
      "34": 92400,
      "35": 43200,
      "41": 186900,
      "42": 65400,
      "43": 133300,
      "44": 26200,
      "51": 240900,
      "52": 320800,
      "53": 146500,
      "54": 47300,
      "61": 115500,
      "62": 5900,
      "71": 173900,
      "72": 176500,
      "73": 16300,
      "74": 81300,
      "75": 70300,
      "81": 57700,
      "82": 19100,
      "83": 150300,
      "91": 142400,
      "92": 5700,
      "93": 143000,
      "94": 33500,
      "96": 18300,
      "02": 5900
    },
    "earnings": {
      "10": 32.07,
      "11": 32.07,
      "12": 32.07,
      "13": 32.07,
      "14": 32.07,
      "15": 32.07,
      "16": 32.07,
      "17": 32.07,
      "18": 32.07,
      "19": 32.07,
      "20": 23.34,
      "21": 23.34,
      "22": 23.34,
      "23": 23.34,
      "24": 23.34,
      "25": 23.34,
      "26": 23.34,
      "27": 23.34,
      "28": 23.34,
      "29": 23.34,
      "30": 19.03,
      "31": 19.03,
      "32": 19.03,
      "33": 19.03,
      "34": 19.03,
      "35": 19.03,
      "36": 19.03,
      "37": 19.03,
      "38": 19.03,
      "39": 19.03,
      "40": 15.24,
      "41": 15.24,
      "42": 15.24,
      "43": 15.24,
      "44": 15.24,
      "45": 15.24,
      "46": 15.24,
      "47": 15.24,
      "48": 15.24,
      "49": 15.24,
      "50": 11.53,
      "51": 11.53,
      "52": 11.53,
      "53": 11.53,
      "54": 11.53,
      "55": 11.53,
      "56": 11.53,
      "57": 11.53,
      "58": 11.53,
      "59": 11.53,
      "70": 15.43,
      "71": 15.43,
      "72": 15.43,
      "73": 15.43,
      "74": 15.43,
      "75": 15.43,
      "76": 15.43,
      "77": 15.43,
      "78": 15.43,
      "79": 15.43,
      "80": 14.69,
      "81": 14.69,
      "82": 14.69,
      "83": 14.69,
      "84": 14.69,
      "85": 14.69,
      "86": 14.69,
      "87": 14.69,
      "88": 14.69,
      "89": 14.69,
      "90": 11.8,
      "91": 11.8,
      "92": 11.8,
      "93": 11.8,
      "94": 11.8,
      "95": 11.8,
      "96": 11.8,
      "97": 11.8,
      "98": 11.8,
      "99": 11.8
    }
  },
  "BE": {
    "employment": {
      "11": 86300,
      "12": 149300,
      "13": 98400,
      "14": 48100,
      "21": 168900,
      "22": 198900,
      "23": 346900,
      "24": 218000,
      "25": 169800,
      "26": 190000,
      "31": 155900,
      "32": 121300,
      "33": 363800,
      "34": 78700,
      "35": 25000,
      "41": 367200,
      "42": 49700,
      "43": 162600,
      "44": 42300,
      "51": 168000,
      "52": 259000,
      "53": 159200,
      "54": 58000,
      "61": 52100,
      "62": 2100,
      "71": 211100,
      "72": 105200,
      "73": 11500,
      "74": 74500,
      "75": 57900,
      "81": 91000,
      "82": 30800,
      "83": 163800,
      "91": 237800,
      "92": 22900,
      "93": 103200,
      "94": 39900,
      "96": 41900,
      "01": 4700,
      "02": 6900,
      "03": 10800
    },
    "earnings": {
      "10": 40.83,
      "11": 40.83,
      "12": 40.83,
      "13": 40.83,
      "14": 40.83,
      "15": 40.83,
      "16": 40.83,
      "17": 40.83,
      "18": 40.83,
      "19": 40.83,
      "20": 30.08,
      "21": 30.08,
      "22": 30.08,
      "23": 30.08,
      "24": 30.08,
      "25": 30.08,
      "26": 30.08,
      "27": 30.08,
      "28": 30.08,
      "29": 30.08,
      "30": 21.18,
      "31": 21.18,
      "32": 21.18,
      "33": 21.18,
      "34": 21.18,
      "35": 21.18,
      "36": 21.18,
      "37": 21.18,
      "38": 21.18,
      "39": 21.18,
      "40": 17.41,
      "41": 17.41,
      "42": 17.41,
      "43": 17.41,
      "44": 17.41,
      "45": 17.41,
      "46": 17.41,
      "47": 17.41,
      "48": 17.41,
      "49": 17.41,
      "50": 14.55,
      "51": 14.55,
      "52": 14.55,
      "53": 14.55,
      "54": 14.55,
      "55": 14.55,
      "56": 14.55,
      "57": 14.55,
      "58": 14.55,
      "59": 14.55,
      "70": 16.65,
      "71": 16.65,
      "72": 16.65,
      "73": 16.65,
      "74": 16.65,
      "75": 16.65,
      "76": 16.65,
      "77": 16.65,
      "78": 16.65,
      "79": 16.65,
      "80": 16.99,
      "81": 16.99,
      "82": 16.99,
      "83": 16.99,
      "84": 16.99,
      "85": 16.99,
      "86": 16.99,
      "87": 16.99,
      "88": 16.99,
      "89": 16.99,
      "90": 13.72,
      "91": 13.72,
      "92": 13.72,
      "93": 13.72,
      "94": 13.72,
      "95": 13.72,
      "96": 13.72,
      "97": 13.72,
      "98": 13.72,
      "99": 13.72
    }
  },
  "BG": {
    "employment": {
      "11": 11600,
      "12": 34300,
      "13": 51400,
      "14": 56100,
      "21": 65099,
      "22": 78500,
      "23": 105700,
      "24": 119100,
      "25": 74900,
      "26": 75400,
      "31": 70600,
      "32": 14600,
      "33": 151200,
      "34": 18400,
      "35": 21300,
      "41": 34700,
      "42": 50700,
      "43": 66700,
      "44": 22000,
      "51": 128199,
      "52": 270600,
      "53": 61300,
      "54": 85200,
      "61": 63900,
      "62": 8500,
      "71": 112500,
      "72": 104100,
      "73": 12800,
      "74": 32800,
      "75": 87000,
      "81": 137700,
      "82": 35600,
      "83": 213200,
      "91": 57300,
      "92": 36400,
      "93": 120200,
      "94": 14700,
      "95": 3100,
      "96": 91600,
      "01": 3500,
      "02": 9000,
      "03": 9600
    },
    "earnings": {
      "10": 5.75,
      "11": 5.75,
      "12": 5.75,
      "13": 5.75,
      "14": 5.75,
      "15": 5.75,
      "16": 5.75,
      "17": 5.75,
      "18": 5.75,
      "19": 5.75,
      "20": 3.6,
      "21": 3.6,
      "22": 3.6,
      "23": 3.6,
      "24": 3.6,
      "25": 3.6,
      "26": 3.6,
      "27": 3.6,
      "28": 3.6,
      "29": 3.6,
      "30": 3.47,
      "31": 3.47,
      "32": 3.47,
      "33": 3.47,
      "34": 3.47,
      "35": 3.47,
      "36": 3.47,
      "37": 3.47,
      "38": 3.47,
      "39": 3.47,
      "40": 2.37,
      "41": 2.37,
      "42": 2.37,
      "43": 2.37,
      "44": 2.37,
      "45": 2.37,
      "46": 2.37,
      "47": 2.37,
      "48": 2.37,
      "49": 2.37,
      "50": 1.69,
      "51": 1.69,
      "52": 1.69,
      "53": 1.69,
      "54": 1.69,
      "55": 1.69,
      "56": 1.69,
      "57": 1.69,
      "58": 1.69,
      "59": 1.69,
      "60": 1.66,
      "61": 1.66,
      "62": 1.66,
      "63": 1.66,
      "64": 1.66,
      "65": 1.66,
      "66": 1.66,
      "67": 1.66,
      "68": 1.66,
      "69": 1.66,
      "70": 2.38,
      "71": 2.38,
      "72": 2.38,
      "73": 2.38,
      "74": 2.38,
      "75": 2.38,
      "76": 2.38,
      "77": 2.38,
      "78": 2.38,
      "79": 2.38,
      "80": 2.19,
      "81": 2.19,
      "82": 2.19,
      "83": 2.19,
      "84": 2.19,
      "85": 2.19,
      "86": 2.19,
      "87": 2.19,
      "88": 2.19,
      "89": 2.19,
      "90": 1.63,
      "91": 1.63,
      "92": 1.63,
      "93": 1.63,
      "94": 1.63,
      "95": 1.63,
      "96": 1.63,
      "97": 1.63,
      "98": 1.63,
      "99": 1.63
    }
  },
  "CY": {
    "employment": {
      "11": 1600,
      "12": 4800,
      "13": 8200,
      "14": 4400,
      "21": 17500,
      "22": 15100,
      "23": 24200,
      "24": 20100,
      "25": 15300,
      "26": 14200,
      "31": 9900,
      "32": 3100,
      "33": 42800,
      "34": 5700,
      "35": 3100,
      "41": 23000,
      "42": 10500,
      "43": 14300,
      "44": 1700,
      "51": 29600,
      "52": 35100,
      "53": 7300,
      "54": 11400,
      "61": 6200,
      "71": 22000,
      "72": 8800,
      "73": 1400,
      "74": 8200,
      "75": 4700,
      "81": 3600,
      "83": 15000,
      "91": 35100,
      "92": 5000,
      "93": 10800,
      "94": 6200,
      "96": 5300,
      "01": 1600,
      "02": 3100,
      "03": 2900
    },
    "earnings": {
      "10": 27.48,
      "11": 27.48,
      "12": 27.48,
      "13": 27.48,
      "14": 27.48,
      "15": 27.48,
      "16": 27.48,
      "17": 27.48,
      "18": 27.48,
      "19": 27.48,
      "20": 16.55,
      "21": 16.55,
      "22": 16.55,
      "23": 16.55,
      "24": 16.55,
      "25": 16.55,
      "26": 16.55,
      "27": 16.55,
      "28": 16.55,
      "29": 16.55,
      "30": 11.67,
      "31": 11.67,
      "32": 11.67,
      "33": 11.67,
      "34": 11.67,
      "35": 11.67,
      "36": 11.67,
      "37": 11.67,
      "38": 11.67,
      "39": 11.67,
      "40": 8.13,
      "41": 8.13,
      "42": 8.13,
      "43": 8.13,
      "44": 8.13,
      "45": 8.13,
      "46": 8.13,
      "47": 8.13,
      "48": 8.13,
      "49": 8.13,
      "50": 6.81,
      "51": 6.81,
      "52": 6.81,
      "53": 6.81,
      "54": 6.81,
      "55": 6.81,
      "56": 6.81,
      "57": 6.81,
      "58": 6.81,
      "59": 6.81,
      "60": 6.68,
      "61": 6.68,
      "62": 6.68,
      "63": 6.68,
      "64": 6.68,
      "65": 6.68,
      "66": 6.68,
      "67": 6.68,
      "68": 6.68,
      "69": 6.68,
      "70": 8.49,
      "71": 8.49,
      "72": 8.49,
      "73": 8.49,
      "74": 8.49,
      "75": 8.49,
      "76": 8.49,
      "77": 8.49,
      "78": 8.49,
      "79": 8.49,
      "80": 9,
      "81": 9,
      "82": 9,
      "83": 9,
      "84": 9,
      "85": 9,
      "86": 9,
      "87": 9,
      "88": 9,
      "89": 9,
      "90": 6.29,
      "91": 6.29,
      "92": 6.29,
      "93": 6.29,
      "94": 6.29,
      "95": 6.29,
      "96": 6.29,
      "97": 6.29,
      "98": 6.29,
      "99": 6.29
    }
  },
  "CZ": {
    "employment": {
      "11": 41800,
      "12": 95200,
      "13": 90100,
      "14": 22600,
      "21": 164600,
      "22": 128199,
      "23": 234900,
      "24": 186900,
      "25": 114300,
      "26": 120700,
      "31": 231600,
      "32": 83200,
      "33": 359100,
      "34": 61300,
      "35": 63800,
      "41": 115100,
      "42": 56700,
      "43": 171900,
      "44": 42000,
      "51": 236500,
      "52": 272800,
      "53": 139700,
      "54": 88200,
      "61": 42400,
      "62": 14900,
      "63": 3900,
      "71": 240700,
      "72": 299900,
      "73": 26300,
      "74": 96900,
      "75": 123000,
      "81": 172400,
      "82": 130199,
      "83": 341900,
      "91": 85600,
      "92": 12800,
      "93": 117400,
      "94": 12700,
      "96": 29800,
      "01": 2400,
      "02": 2900,
      "03": 12000
    },
    "earnings": {
      "10": 11.57,
      "11": 11.57,
      "12": 11.57,
      "13": 11.57,
      "14": 11.57,
      "15": 11.57,
      "16": 11.57,
      "17": 11.57,
      "18": 11.57,
      "19": 11.57,
      "20": 8.39,
      "21": 8.39,
      "22": 8.39,
      "23": 8.39,
      "24": 8.39,
      "25": 8.39,
      "26": 8.39,
      "27": 8.39,
      "28": 8.39,
      "29": 8.39,
      "30": 7.5,
      "31": 7.5,
      "32": 7.5,
      "33": 7.5,
      "34": 7.5,
      "35": 7.5,
      "36": 7.5,
      "37": 7.5,
      "38": 7.5,
      "39": 7.5,
      "40": 5.73,
      "41": 5.73,
      "42": 5.73,
      "43": 5.73,
      "44": 5.73,
      "45": 5.73,
      "46": 5.73,
      "47": 5.73,
      "48": 5.73,
      "49": 5.73,
      "50": 4.67,
      "51": 4.67,
      "52": 4.67,
      "53": 4.67,
      "54": 4.67,
      "55": 4.67,
      "56": 4.67,
      "57": 4.67,
      "58": 4.67,
      "59": 4.67,
      "60": 4.46,
      "61": 4.46,
      "62": 4.46,
      "63": 4.46,
      "64": 4.46,
      "65": 4.46,
      "66": 4.46,
      "67": 4.46,
      "68": 4.46,
      "69": 4.46,
      "70": 6.11,
      "71": 6.11,
      "72": 6.11,
      "73": 6.11,
      "74": 6.11,
      "75": 6.11,
      "76": 6.11,
      "77": 6.11,
      "78": 6.11,
      "79": 6.11,
      "80": 5.71,
      "81": 5.71,
      "82": 5.71,
      "83": 5.71,
      "84": 5.71,
      "85": 5.71,
      "86": 5.71,
      "87": 5.71,
      "88": 5.71,
      "89": 5.71,
      "90": 4.04,
      "91": 4.04,
      "92": 4.04,
      "93": 4.04,
      "94": 4.04,
      "95": 4.04,
      "96": 4.04,
      "97": 4.04,
      "98": 4.04,
      "99": 4.04,
      "00": 11.94,
      "01": 11.94,
      "02": 11.94,
      "03": 11.94,
      "04": 11.94,
      "05": 11.94,
      "06": 11.94,
      "07": 11.94,
      "08": 11.94,
      "09": 11.94
    }
  },
  "DE": {
    "employment": {
      "11": 548800,
      "12": 468700,
      "13": 499500,
      "14": 215300,
      "21": 1717700,
      "22": 982300,
      "23": 2463900,
      "24": 1690300,
      "25": 1025700,
      "26": 1334000,
      "31": 1729100,
      "32": 2609400,
      "33": 2882700,
      "34": 530000,
      "35": 323600,
      "41": 2745900,
      "42": 607300,
      "43": 1548400,
      "44": 438500,
      "51": 1858400,
      "52": 2428700,
      "53": 763900,
      "54": 500700,
      "61": 477400,
      "62": 24400,
      "71": 1055200,
      "72": 1862400,
      "73": 187700,
      "74": 698800,
      "75": 614800,
      "81": 964400,
      "82": 337900,
      "83": 1187600,
      "91": 1107800,
      "92": 122100,
      "93": 1175400,
      "94": 315700,
      "96": 212400,
      "03": 153200
    },
    "earnings": {
      "10": 40.13,
      "11": 40.13,
      "12": 40.13,
      "13": 40.13,
      "14": 40.13,
      "15": 40.13,
      "16": 40.13,
      "17": 40.13,
      "18": 40.13,
      "19": 40.13,
      "20": 28.45,
      "21": 28.45,
      "22": 28.45,
      "23": 28.45,
      "24": 28.45,
      "25": 28.45,
      "26": 28.45,
      "27": 28.45,
      "28": 28.45,
      "29": 28.45,
      "30": 21.02,
      "31": 21.02,
      "32": 21.02,
      "33": 21.02,
      "34": 21.02,
      "35": 21.02,
      "36": 21.02,
      "37": 21.02,
      "38": 21.02,
      "39": 21.02,
      "40": 17.05,
      "41": 17.05,
      "42": 17.05,
      "43": 17.05,
      "44": 17.05,
      "45": 17.05,
      "46": 17.05,
      "47": 17.05,
      "48": 17.05,
      "49": 17.05,
      "50": 13.38,
      "51": 13.38,
      "52": 13.38,
      "53": 13.38,
      "54": 13.38,
      "55": 13.38,
      "56": 13.38,
      "57": 13.38,
      "58": 13.38,
      "59": 13.38,
      "60": 15,
      "61": 15,
      "62": 15,
      "63": 15,
      "64": 15,
      "65": 15,
      "66": 15,
      "67": 15,
      "68": 15,
      "69": 15,
      "70": 17.5,
      "71": 17.5,
      "72": 17.5,
      "73": 17.5,
      "74": 17.5,
      "75": 17.5,
      "76": 17.5,
      "77": 17.5,
      "78": 17.5,
      "79": 17.5,
      "80": 15.81,
      "81": 15.81,
      "82": 15.81,
      "83": 15.81,
      "84": 15.81,
      "85": 15.81,
      "86": 15.81,
      "87": 15.81,
      "88": 15.81,
      "89": 15.81,
      "90": 12.01,
      "91": 12.01,
      "92": 12.01,
      "93": 12.01,
      "94": 12.01,
      "95": 12.01,
      "96": 12.01,
      "97": 12.01,
      "98": 12.01,
      "99": 12.01,
      "00": 13.21,
      "01": 13.21,
      "02": 13.21,
      "03": 13.21,
      "04": 13.21,
      "05": 13.21,
      "06": 13.21,
      "07": 13.21,
      "08": 13.21,
      "09": 13.21
    }
  },
  "DK": {
    "employment": {
      "11": 10000,
      "12": 23200,
      "13": 28000,
      "14": 10800,
      "21": 97400,
      "22": 138300,
      "23": 198200,
      "24": 206600,
      "25": 97800,
      "26": 89300,
      "31": 138800,
      "32": 36300,
      "33": 244100,
      "34": 45600,
      "35": 50300,
      "41": 71000,
      "42": 32200,
      "43": 60200,
      "44": 19300,
      "51": 103800,
      "52": 182500,
      "53": 217800,
      "54": 23000,
      "61": 37300,
      "71": 88500,
      "72": 64900,
      "73": 7600,
      "74": 30500,
      "75": 16100,
      "81": 43600,
      "82": 13500,
      "83": 81100,
      "91": 67800,
      "92": 18200,
      "93": 115500,
      "94": 60800,
      "96": 35300,
      "01": 3500,
      "02": 3100,
      "03": 5300
    },
    "earnings": {
      "10": 43.27,
      "11": 43.27,
      "12": 43.27,
      "13": 43.27,
      "14": 43.27,
      "15": 43.27,
      "16": 43.27,
      "17": 43.27,
      "18": 43.27,
      "19": 43.27,
      "20": 31.94,
      "21": 31.94,
      "22": 31.94,
      "23": 31.94,
      "24": 31.94,
      "25": 31.94,
      "26": 31.94,
      "27": 31.94,
      "28": 31.94,
      "29": 31.94,
      "30": 30.61,
      "31": 30.61,
      "32": 30.61,
      "33": 30.61,
      "34": 30.61,
      "35": 30.61,
      "36": 30.61,
      "37": 30.61,
      "38": 30.61,
      "39": 30.61,
      "40": 26.56,
      "41": 26.56,
      "42": 26.56,
      "43": 26.56,
      "44": 26.56,
      "45": 26.56,
      "46": 26.56,
      "47": 26.56,
      "48": 26.56,
      "49": 26.56,
      "50": 22.72,
      "51": 22.72,
      "52": 22.72,
      "53": 22.72,
      "54": 22.72,
      "55": 22.72,
      "56": 22.72,
      "57": 22.72,
      "58": 22.72,
      "59": 22.72,
      "60": 24.68,
      "61": 24.68,
      "62": 24.68,
      "63": 24.68,
      "64": 24.68,
      "65": 24.68,
      "66": 24.68,
      "67": 24.68,
      "68": 24.68,
      "69": 24.68,
      "70": 29.3,
      "71": 29.3,
      "72": 29.3,
      "73": 29.3,
      "74": 29.3,
      "75": 29.3,
      "76": 29.3,
      "77": 29.3,
      "78": 29.3,
      "79": 29.3,
      "80": 27.13,
      "81": 27.13,
      "82": 27.13,
      "83": 27.13,
      "84": 27.13,
      "85": 27.13,
      "86": 27.13,
      "87": 27.13,
      "88": 27.13,
      "89": 27.13,
      "90": 23.55,
      "91": 23.55,
      "92": 23.55,
      "93": 23.55,
      "94": 23.55,
      "95": 23.55,
      "96": 23.55,
      "97": 23.55,
      "98": 23.55,
      "99": 23.55
    }
  },
  "EE": {
    "employment": {
      "12": 5400,
      "13": 32600,
      "14": 12800,
      "21": 22700,
      "22": 19200,
      "23": 35500,
      "24": 39400,
      "25": 27900,
      "26": 18300,
      "31": 19900,
      "32": 8400,
      "33": 49300,
      "34": 11500,
      "35": 5900,
      "41": 3200,
      "42": 13100,
      "43": 22900,
      "44": 5700,
      "51": 24700,
      "52": 30600,
      "53": 17600,
      "54": 7100,
      "61": 5000,
      "62": 2800,
      "71": 31700,
      "72": 31100,
      "73": 3200,
      "74": 9600,
      "75": 15300,
      "81": 18600,
      "82": 8700,
      "83": 39300,
      "91": 14400,
      "92": 2900,
      "93": 13800,
      "94": 4500,
      "96": 13800,
      "02": 1900
    },
    "earnings": {
      "10": 10.59,
      "11": 10.59,
      "12": 10.59,
      "13": 10.59,
      "14": 10.59,
      "15": 10.59,
      "16": 10.59,
      "17": 10.59,
      "18": 10.59,
      "19": 10.59,
      "20": 8.8,
      "21": 8.8,
      "22": 8.8,
      "23": 8.8,
      "24": 8.8,
      "25": 8.8,
      "26": 8.8,
      "27": 8.8,
      "28": 8.8,
      "29": 8.8,
      "30": 7.5,
      "31": 7.5,
      "32": 7.5,
      "33": 7.5,
      "34": 7.5,
      "35": 7.5,
      "36": 7.5,
      "37": 7.5,
      "38": 7.5,
      "39": 7.5,
      "40": 6.25,
      "41": 6.25,
      "42": 6.25,
      "43": 6.25,
      "44": 6.25,
      "45": 6.25,
      "46": 6.25,
      "47": 6.25,
      "48": 6.25,
      "49": 6.25,
      "50": 4.42,
      "51": 4.42,
      "52": 4.42,
      "53": 4.42,
      "54": 4.42,
      "55": 4.42,
      "56": 4.42,
      "57": 4.42,
      "58": 4.42,
      "59": 4.42,
      "60": 4.79,
      "61": 4.79,
      "62": 4.79,
      "63": 4.79,
      "64": 4.79,
      "65": 4.79,
      "66": 4.79,
      "67": 4.79,
      "68": 4.79,
      "69": 4.79,
      "70": 6.54,
      "71": 6.54,
      "72": 6.54,
      "73": 6.54,
      "74": 6.54,
      "75": 6.54,
      "76": 6.54,
      "77": 6.54,
      "78": 6.54,
      "79": 6.54,
      "80": 5.97,
      "81": 5.97,
      "82": 5.97,
      "83": 5.97,
      "84": 5.97,
      "85": 5.97,
      "86": 5.97,
      "87": 5.97,
      "88": 5.97,
      "89": 5.97,
      "90": 4.33,
      "91": 4.33,
      "92": 4.33,
      "93": 4.33,
      "94": 4.33,
      "95": 4.33,
      "96": 4.33,
      "97": 4.33,
      "98": 4.33,
      "99": 4.33
    }
  },
  "EL": {
    "employment": {
      "11": 6400,
      "12": 25600,
      "13": 40400,
      "14": 49300,
      "21": 137000,
      "22": 182200,
      "23": 277900,
      "24": 131100,
      "25": 42300,
      "26": 123100,
      "31": 72500,
      "32": 32400,
      "33": 130600,
      "34": 35400,
      "35": 17500,
      "41": 283400,
      "42": 74600,
      "43": 65800,
      "44": 22100,
      "51": 267400,
      "52": 498900,
      "53": 36400,
      "54": 109600,
      "61": 389100,
      "62": 9900,
      "71": 127100,
      "72": 98100,
      "73": 12200,
      "74": 69000,
      "75": 82600,
      "81": 66400,
      "82": 2900,
      "83": 213400,
      "91": 102100,
      "92": 39600,
      "93": 65700,
      "94": 31900,
      "96": 38300,
      "01": 39100,
      "02": 22800,
      "03": 4500
    },
    "earnings": {
      "10": 17,
      "11": 17,
      "12": 17,
      "13": 17,
      "14": 17,
      "15": 17,
      "16": 17,
      "17": 17,
      "18": 17,
      "19": 17,
      "20": 12,
      "21": 12,
      "22": 12,
      "23": 12,
      "24": 12,
      "25": 12,
      "26": 12,
      "27": 12,
      "28": 12,
      "29": 12,
      "30": 8,
      "31": 8,
      "32": 8,
      "33": 8,
      "34": 8,
      "35": 8,
      "36": 8,
      "37": 8,
      "38": 8,
      "39": 8,
      "40": 8,
      "41": 8,
      "42": 8,
      "43": 8,
      "44": 8,
      "45": 8,
      "46": 8,
      "47": 8,
      "48": 8,
      "49": 8,
      "50": 6,
      "51": 6,
      "52": 6,
      "53": 6,
      "54": 6,
      "55": 6,
      "56": 6,
      "57": 6,
      "58": 6,
      "59": 6,
      "70": 7,
      "71": 7,
      "72": 7,
      "73": 7,
      "74": 7,
      "75": 7,
      "76": 7,
      "77": 7,
      "78": 7,
      "79": 7,
      "80": 7,
      "81": 7,
      "82": 7,
      "83": 7,
      "84": 7,
      "85": 7,
      "86": 7,
      "87": 7,
      "88": 7,
      "89": 7,
      "90": 5,
      "91": 5,
      "92": 5,
      "93": 5,
      "94": 5,
      "95": 5,
      "96": 5,
      "97": 5,
      "98": 5,
      "99": 5
    }
  },
  "ES": {
    "employment": {
      "11": 45800,
      "12": 257399,
      "13": 238400,
      "14": 291500,
      "21": 692400,
      "22": 787100,
      "23": 1161000,
      "24": 548300,
      "25": 246900,
      "26": 613500,
      "31": 464400,
      "32": 249900,
      "33": 1086700,
      "34": 330000,
      "35": 394900,
      "41": 512500,
      "42": 933900,
      "43": 580800,
      "44": 63600,
      "51": 993200,
      "52": 2084600,
      "53": 831000,
      "54": 475200,
      "61": 390100,
      "62": 34100,
      "71": 934700,
      "72": 542600,
      "73": 78800,
      "74": 368500,
      "75": 317500,
      "81": 456000,
      "82": 146700,
      "83": 1056600,
      "91": 1137700,
      "92": 336000,
      "93": 714300,
      "94": 186600,
      "95": 5000,
      "96": 163000,
      "01": 16200,
      "02": 27600,
      "03": 56700
    },
    "earnings": {
      "10": 21.8,
      "11": 21.8,
      "12": 21.8,
      "13": 21.8,
      "14": 21.8,
      "15": 21.8,
      "16": 21.8,
      "17": 21.8,
      "18": 21.8,
      "19": 21.8,
      "20": 16.54,
      "21": 16.54,
      "22": 16.54,
      "23": 16.54,
      "24": 16.54,
      "25": 16.54,
      "26": 16.54,
      "27": 16.54,
      "28": 16.54,
      "29": 16.54,
      "30": 12.77,
      "31": 12.77,
      "32": 12.77,
      "33": 12.77,
      "34": 12.77,
      "35": 12.77,
      "36": 12.77,
      "37": 12.77,
      "38": 12.77,
      "39": 12.77,
      "40": 9.9,
      "41": 9.9,
      "42": 9.9,
      "43": 9.9,
      "44": 9.9,
      "45": 9.9,
      "46": 9.9,
      "47": 9.9,
      "48": 9.9,
      "49": 9.9,
      "50": 8.08,
      "51": 8.08,
      "52": 8.08,
      "53": 8.08,
      "54": 8.08,
      "55": 8.08,
      "56": 8.08,
      "57": 8.08,
      "58": 8.08,
      "59": 8.08,
      "60": 8.44,
      "61": 8.44,
      "62": 8.44,
      "63": 8.44,
      "64": 8.44,
      "65": 8.44,
      "66": 8.44,
      "67": 8.44,
      "68": 8.44,
      "69": 8.44,
      "70": 9.64,
      "71": 9.64,
      "72": 9.64,
      "73": 9.64,
      "74": 9.64,
      "75": 9.64,
      "76": 9.64,
      "77": 9.64,
      "78": 9.64,
      "79": 9.64,
      "80": 10.26,
      "81": 10.26,
      "82": 10.26,
      "83": 10.26,
      "84": 10.26,
      "85": 10.26,
      "86": 10.26,
      "87": 10.26,
      "88": 10.26,
      "89": 10.26,
      "90": 7.99,
      "91": 7.99,
      "92": 7.99,
      "93": 7.99,
      "94": 7.99,
      "95": 7.99,
      "96": 7.99,
      "97": 7.99,
      "98": 7.99,
      "99": 7.99
    }
  },
  "FI": {
    "employment": {
      "11": 6900,
      "12": 26800,
      "13": 30400,
      "14": 8800,
      "21": 160400,
      "22": 41300,
      "23": 134600,
      "24": 154300,
      "25": 110100,
      "26": 85300,
      "31": 102100,
      "32": 103700,
      "33": 162400,
      "34": 87800,
      "35": 29400,
      "41": 32700,
      "42": 33500,
      "43": 35300,
      "44": 20500,
      "51": 115300,
      "52": 156300,
      "53": 186800,
      "54": 18600,
      "61": 52500,
      "62": 6300,
      "71": 93800,
      "72": 85700,
      "73": 7100,
      "74": 39100,
      "75": 21600,
      "81": 56700,
      "82": 18600,
      "83": 109700,
      "91": 66900,
      "92": 4200,
      "93": 55300,
      "94": 28500,
      "95": 3500,
      "96": 11100,
      "01": 3500,
      "02": 3600
    },
    "earnings": {
      "10": 38.85,
      "11": 38.85,
      "12": 38.85,
      "13": 38.85,
      "14": 38.85,
      "15": 38.85,
      "16": 38.85,
      "17": 38.85,
      "18": 38.85,
      "19": 38.85,
      "20": 23.91,
      "21": 23.91,
      "22": 23.91,
      "23": 23.91,
      "24": 23.91,
      "25": 23.91,
      "26": 23.91,
      "27": 23.91,
      "28": 23.91,
      "29": 23.91,
      "30": 19.08,
      "31": 19.08,
      "32": 19.08,
      "33": 19.08,
      "34": 19.08,
      "35": 19.08,
      "36": 19.08,
      "37": 19.08,
      "38": 19.08,
      "39": 19.08,
      "40": 16.14,
      "41": 16.14,
      "42": 16.14,
      "43": 16.14,
      "44": 16.14,
      "45": 16.14,
      "46": 16.14,
      "47": 16.14,
      "48": 16.14,
      "49": 16.14,
      "50": 14.72,
      "51": 14.72,
      "52": 14.72,
      "53": 14.72,
      "54": 14.72,
      "55": 14.72,
      "56": 14.72,
      "57": 14.72,
      "58": 14.72,
      "59": 14.72,
      "60": 13.44,
      "61": 13.44,
      "62": 13.44,
      "63": 13.44,
      "64": 13.44,
      "65": 13.44,
      "66": 13.44,
      "67": 13.44,
      "68": 13.44,
      "69": 13.44,
      "70": 17.08,
      "71": 17.08,
      "72": 17.08,
      "73": 17.08,
      "74": 17.08,
      "75": 17.08,
      "76": 17.08,
      "77": 17.08,
      "78": 17.08,
      "79": 17.08,
      "80": 16.87,
      "81": 16.87,
      "82": 16.87,
      "83": 16.87,
      "84": 16.87,
      "85": 16.87,
      "86": 16.87,
      "87": 16.87,
      "88": 16.87,
      "89": 16.87,
      "90": 12.84,
      "91": 12.84,
      "92": 12.84,
      "93": 12.84,
      "94": 12.84,
      "95": 12.84,
      "96": 12.84,
      "97": 12.84,
      "98": 12.84,
      "99": 12.84
    }
  },
  "FR": {
    "employment": {
      "11": 182800,
      "12": 599900,
      "13": 666200,
      "14": 485600,
      "21": 1201000,
      "22": 797700,
      "23": 1297700,
      "24": 1673900,
      "25": 820300,
      "26": 820900,
      "31": 959800,
      "32": 992300,
      "33": 1923300,
      "34": 1026800,
      "35": 210600,
      "41": 970800,
      "42": 299100,
      "43": 729500,
      "44": 276900,
      "51": 992900,
      "52": 1226700,
      "53": 1340700,
      "54": 453700,
      "61": 681000,
      "62": 42500,
      "71": 981700,
      "72": 808800,
      "73": 108900,
      "74": 277800,
      "75": 497900,
      "81": 583900,
      "82": 150200,
      "83": 1075800,
      "91": 1094200,
      "92": 139200,
      "93": 663700,
      "94": 225900,
      "96": 226900,
      "01": 35000,
      "02": 82100,
      "03": 76300
    },
    "earnings": {
      "10": 24.78,
      "11": 24.78,
      "12": 24.78,
      "13": 24.78,
      "14": 24.78,
      "15": 24.78,
      "16": 24.78,
      "17": 24.78,
      "18": 24.78,
      "19": 24.78,
      "20": 21.46,
      "21": 21.46,
      "22": 21.46,
      "23": 21.46,
      "24": 21.46,
      "25": 21.46,
      "26": 21.46,
      "27": 21.46,
      "28": 21.46,
      "29": 21.46,
      "30": 17.05,
      "31": 17.05,
      "32": 17.05,
      "33": 17.05,
      "34": 17.05,
      "35": 17.05,
      "36": 17.05,
      "37": 17.05,
      "38": 17.05,
      "39": 17.05,
      "40": 13.04,
      "41": 13.04,
      "42": 13.04,
      "43": 13.04,
      "44": 13.04,
      "45": 13.04,
      "46": 13.04,
      "47": 13.04,
      "48": 13.04,
      "49": 13.04,
      "50": 12.87,
      "51": 12.87,
      "52": 12.87,
      "53": 12.87,
      "54": 12.87,
      "55": 12.87,
      "56": 12.87,
      "57": 12.87,
      "58": 12.87,
      "59": 12.87,
      "60": 12.62,
      "61": 12.62,
      "62": 12.62,
      "63": 12.62,
      "64": 12.62,
      "65": 12.62,
      "66": 12.62,
      "67": 12.62,
      "68": 12.62,
      "69": 12.62,
      "70": 13.96,
      "71": 13.96,
      "72": 13.96,
      "73": 13.96,
      "74": 13.96,
      "75": 13.96,
      "76": 13.96,
      "77": 13.96,
      "78": 13.96,
      "79": 13.96,
      "80": 13.71,
      "81": 13.71,
      "82": 13.71,
      "83": 13.71,
      "84": 13.71,
      "85": 13.71,
      "86": 13.71,
      "87": 13.71,
      "88": 13.71,
      "89": 13.71,
      "90": 11.56,
      "91": 11.56,
      "92": 11.56,
      "93": 11.56,
      "94": 11.56,
      "95": 11.56,
      "96": 11.56,
      "97": 11.56,
      "98": 11.56,
      "99": 11.56
    }
  },
  "HR": {
    "employment": {
      "11": 4600,
      "12": 14300,
      "13": 45600,
      "14": 29300,
      "21": 49600,
      "22": 35800,
      "23": 93600,
      "24": 44000,
      "25": 31800,
      "26": 73000,
      "31": 63900,
      "32": 38700,
      "33": 86000,
      "34": 13300,
      "35": 13200,
      "41": 38600,
      "42": 29100,
      "43": 60300,
      "44": 8700,
      "51": 95900,
      "52": 128500,
      "53": 27400,
      "54": 40800,
      "61": 33900,
      "62": 2900,
      "71": 50300,
      "72": 76300,
      "73": 6400,
      "74": 36000,
      "75": 24200,
      "81": 56100,
      "82": 9300,
      "83": 87300,
      "91": 47300,
      "92": 21200,
      "93": 37000,
      "94": 2200,
      "96": 14900,
      "01": 2900,
      "02": 1800,
      "03": 7100
    },
    "earnings": {
      "10": 9.44,
      "11": 9.44,
      "12": 9.44,
      "13": 9.44,
      "14": 9.44,
      "15": 9.44,
      "16": 9.44,
      "17": 9.44,
      "18": 9.44,
      "19": 9.44,
      "20": 7.81,
      "21": 7.81,
      "22": 7.81,
      "23": 7.81,
      "24": 7.81,
      "25": 7.81,
      "26": 7.81,
      "27": 7.81,
      "28": 7.81,
      "29": 7.81,
      "30": 6.31,
      "31": 6.31,
      "32": 6.31,
      "33": 6.31,
      "34": 6.31,
      "35": 6.31,
      "36": 6.31,
      "37": 6.31,
      "38": 6.31,
      "39": 6.31,
      "40": 5.47,
      "41": 5.47,
      "42": 5.47,
      "43": 5.47,
      "44": 5.47,
      "45": 5.47,
      "46": 5.47,
      "47": 5.47,
      "48": 5.47,
      "49": 5.47,
      "50": 4.12,
      "51": 4.12,
      "52": 4.12,
      "53": 4.12,
      "54": 4.12,
      "55": 4.12,
      "56": 4.12,
      "57": 4.12,
      "58": 4.12,
      "59": 4.12,
      "60": 3.94,
      "61": 3.94,
      "62": 3.94,
      "63": 3.94,
      "64": 3.94,
      "65": 3.94,
      "66": 3.94,
      "67": 3.94,
      "68": 3.94,
      "69": 3.94,
      "70": 4.51,
      "71": 4.51,
      "72": 4.51,
      "73": 4.51,
      "74": 4.51,
      "75": 4.51,
      "76": 4.51,
      "77": 4.51,
      "78": 4.51,
      "79": 4.51,
      "80": 4.97,
      "81": 4.97,
      "82": 4.97,
      "83": 4.97,
      "84": 4.97,
      "85": 4.97,
      "86": 4.97,
      "87": 4.97,
      "88": 4.97,
      "89": 4.97,
      "90": 3.77,
      "91": 3.77,
      "92": 3.77,
      "93": 3.77,
      "94": 3.77,
      "95": 3.77,
      "96": 3.77,
      "97": 3.77,
      "98": 3.77,
      "99": 3.77
    }
  },
  "HU": {
    "employment": {
      "11": 8300,
      "12": 39500,
      "13": 87100,
      "14": 43200,
      "21": 147200,
      "22": 62000,
      "23": 233900,
      "24": 150000,
      "25": 118000,
      "26": 139300,
      "31": 120400,
      "32": 120100,
      "33": 378900,
      "34": 71700,
      "35": 26200,
      "41": 140500,
      "42": 60200,
      "43": 154700,
      "44": 33600,
      "51": 188800,
      "52": 302000,
      "53": 74800,
      "54": 96500,
      "61": 101300,
      "62": 12100,
      "71": 201000,
      "72": 223000,
      "73": 21600,
      "74": 84400,
      "75": 111900,
      "81": 187500,
      "82": 149100,
      "83": 251400,
      "91": 112300,
      "92": 55400,
      "93": 144400,
      "94": 43400,
      "96": 56600,
      "01": 7500,
      "02": 14000
    },
    "earnings": {
      "10": 8.23,
      "11": 8.23,
      "12": 8.23,
      "13": 8.23,
      "14": 8.23,
      "15": 8.23,
      "16": 8.23,
      "17": 8.23,
      "18": 8.23,
      "19": 8.23,
      "20": 6.65,
      "21": 6.65,
      "22": 6.65,
      "23": 6.65,
      "24": 6.65,
      "25": 6.65,
      "26": 6.65,
      "27": 6.65,
      "28": 6.65,
      "29": 6.65,
      "30": 4.99,
      "31": 4.99,
      "32": 4.99,
      "33": 4.99,
      "34": 4.99,
      "35": 4.99,
      "36": 4.99,
      "37": 4.99,
      "38": 4.99,
      "39": 4.99,
      "40": 4.48,
      "41": 4.48,
      "42": 4.48,
      "43": 4.48,
      "44": 4.48,
      "45": 4.48,
      "46": 4.48,
      "47": 4.48,
      "48": 4.48,
      "49": 4.48,
      "50": 3.63,
      "51": 3.63,
      "52": 3.63,
      "53": 3.63,
      "54": 3.63,
      "55": 3.63,
      "56": 3.63,
      "57": 3.63,
      "58": 3.63,
      "59": 3.63,
      "60": 3.52,
      "61": 3.52,
      "62": 3.52,
      "63": 3.52,
      "64": 3.52,
      "65": 3.52,
      "66": 3.52,
      "67": 3.52,
      "68": 3.52,
      "69": 3.52,
      "70": 4.34,
      "71": 4.34,
      "72": 4.34,
      "73": 4.34,
      "74": 4.34,
      "75": 4.34,
      "76": 4.34,
      "77": 4.34,
      "78": 4.34,
      "79": 4.34,
      "80": 4.08,
      "81": 4.08,
      "82": 4.08,
      "83": 4.08,
      "84": 4.08,
      "85": 4.08,
      "86": 4.08,
      "87": 4.08,
      "88": 4.08,
      "89": 4.08,
      "90": 3.08,
      "91": 3.08,
      "92": 3.08,
      "93": 3.08,
      "94": 3.08,
      "95": 3.08,
      "96": 3.08,
      "97": 3.08,
      "98": 3.08,
      "99": 3.08,
      "00": 8.41,
      "01": 8.41,
      "02": 8.41,
      "03": 8.41,
      "04": 8.41,
      "05": 8.41,
      "06": 8.41,
      "07": 8.41,
      "08": 8.41,
      "09": 8.41
    }
  },
  "IE": {
    "employment": {
      "11": 7200,
      "12": 54400,
      "13": 93900,
      "14": 85400,
      "21": 107400,
      "22": 132000,
      "23": 130800,
      "24": 168100,
      "25": 96000,
      "26": 56800,
      "31": 45100,
      "32": 29100,
      "33": 147500,
      "34": 66400,
      "35": 30000,
      "41": 34800,
      "42": 53700,
      "43": 55200,
      "44": 75700,
      "51": 115800,
      "52": 170200,
      "53": 144100,
      "54": 34300,
      "61": 61700,
      "71": 74200,
      "72": 57300,
      "73": 8500,
      "74": 38900,
      "75": 46700,
      "81": 31900,
      "82": 24000,
      "83": 75100,
      "91": 49100,
      "92": 16100,
      "93": 64599,
      "94": 40600,
      "96": 26400
    },
    "earnings": {
      "10": 25.72,
      "11": 25.72,
      "12": 25.72,
      "13": 25.72,
      "14": 25.72,
      "15": 25.72,
      "16": 25.72,
      "17": 25.72,
      "18": 25.72,
      "19": 25.72,
      "20": 27.75,
      "21": 27.75,
      "22": 27.75,
      "23": 27.75,
      "24": 27.75,
      "25": 27.75,
      "26": 27.75,
      "27": 27.75,
      "28": 27.75,
      "29": 27.75,
      "30": 20.49,
      "31": 20.49,
      "32": 20.49,
      "33": 20.49,
      "34": 20.49,
      "35": 20.49,
      "36": 20.49,
      "37": 20.49,
      "38": 20.49,
      "39": 20.49,
      "40": 15.6,
      "41": 15.6,
      "42": 15.6,
      "43": 15.6,
      "44": 15.6,
      "45": 15.6,
      "46": 15.6,
      "47": 15.6,
      "48": 15.6,
      "49": 15.6,
      "50": 13.67,
      "51": 13.67,
      "52": 13.67,
      "53": 13.67,
      "54": 13.67,
      "55": 13.67,
      "56": 13.67,
      "57": 13.67,
      "58": 13.67,
      "59": 13.67,
      "60": 13.88,
      "61": 13.88,
      "62": 13.88,
      "63": 13.88,
      "64": 13.88,
      "65": 13.88,
      "66": 13.88,
      "67": 13.88,
      "68": 13.88,
      "69": 13.88,
      "70": 15.27,
      "71": 15.27,
      "72": 15.27,
      "73": 15.27,
      "74": 15.27,
      "75": 15.27,
      "76": 15.27,
      "77": 15.27,
      "78": 15.27,
      "79": 15.27,
      "80": 15.26,
      "81": 15.26,
      "82": 15.26,
      "83": 15.26,
      "84": 15.26,
      "85": 15.26,
      "86": 15.26,
      "87": 15.26,
      "88": 15.26,
      "89": 15.26,
      "90": 12.82,
      "91": 12.82,
      "92": 12.82,
      "93": 12.82,
      "94": 12.82,
      "95": 12.82,
      "96": 12.82,
      "97": 12.82,
      "98": 12.82,
      "99": 12.82
    }
  },
  "IT": {
    "employment": {
      "11": 74300,
      "12": 51300,
      "13": 280700,
      "14": 398500,
      "21": 608300,
      "22": 302300,
      "23": 1293300,
      "24": 530500,
      "25": 233500,
      "26": 515600,
      "31": 940000,
      "32": 802000,
      "33": 1658700,
      "34": 245200,
      "35": 407800,
      "41": 1526200,
      "42": 493700,
      "43": 695400,
      "44": 199300,
      "51": 1298000,
      "52": 1641100,
      "53": 723600,
      "54": 291700,
      "61": 453700,
      "62": 23300,
      "71": 944600,
      "72": 904800,
      "73": 204800,
      "74": 352300,
      "75": 576800,
      "81": 654200,
      "82": 159500,
      "83": 723100,
      "91": 905900,
      "92": 367700,
      "93": 507900,
      "94": 99200,
      "95": 66200,
      "96": 458800,
      "01": 34400,
      "02": 70800,
      "03": 116000
    },
    "earnings": {
      "10": 38.82,
      "11": 38.82,
      "12": 38.82,
      "13": 38.82,
      "14": 38.82,
      "15": 38.82,
      "16": 38.82,
      "17": 38.82,
      "18": 38.82,
      "19": 38.82,
      "20": 23.5,
      "21": 23.5,
      "22": 23.5,
      "23": 23.5,
      "24": 23.5,
      "25": 23.5,
      "26": 23.5,
      "27": 23.5,
      "28": 23.5,
      "29": 23.5,
      "30": 15.74,
      "31": 15.74,
      "32": 15.74,
      "33": 15.74,
      "34": 15.74,
      "35": 15.74,
      "36": 15.74,
      "37": 15.74,
      "38": 15.74,
      "39": 15.74,
      "40": 12.42,
      "41": 12.42,
      "42": 12.42,
      "43": 12.42,
      "44": 12.42,
      "45": 12.42,
      "46": 12.42,
      "47": 12.42,
      "48": 12.42,
      "49": 12.42,
      "50": 10.54,
      "51": 10.54,
      "52": 10.54,
      "53": 10.54,
      "54": 10.54,
      "55": 10.54,
      "56": 10.54,
      "57": 10.54,
      "58": 10.54,
      "59": 10.54,
      "60": 11.85,
      "61": 11.85,
      "62": 11.85,
      "63": 11.85,
      "64": 11.85,
      "65": 11.85,
      "66": 11.85,
      "67": 11.85,
      "68": 11.85,
      "69": 11.85,
      "70": 11.37,
      "71": 11.37,
      "72": 11.37,
      "73": 11.37,
      "74": 11.37,
      "75": 11.37,
      "76": 11.37,
      "77": 11.37,
      "78": 11.37,
      "79": 11.37,
      "80": 11.95,
      "81": 11.95,
      "82": 11.95,
      "83": 11.95,
      "84": 11.95,
      "85": 11.95,
      "86": 11.95,
      "87": 11.95,
      "88": 11.95,
      "89": 11.95,
      "90": 10.13,
      "91": 10.13,
      "92": 10.13,
      "93": 10.13,
      "94": 10.13,
      "95": 10.13,
      "96": 10.13,
      "97": 10.13,
      "98": 10.13,
      "99": 10.13,
      "00": 19.5,
      "01": 19.5,
      "02": 19.5,
      "03": 19.5,
      "04": 19.5,
      "05": 19.5,
      "06": 19.5,
      "07": 19.5,
      "08": 19.5,
      "09": 19.5
    }
  },
  "LT": {
    "employment": {
      "11": 35600,
      "12": 48100,
      "13": 29200,
      "14": 9100,
      "21": 45900,
      "22": 49200,
      "23": 60300,
      "24": 151400,
      "25": 47000,
      "26": 43700,
      "31": 31400,
      "32": 17300,
      "33": 62300,
      "34": 19000,
      "35": 4700,
      "41": 9900,
      "42": 14000,
      "43": 24400,
      "44": 9800,
      "51": 52700,
      "52": 77200,
      "53": 19500,
      "54": 14800,
      "61": 29800,
      "62": 2100,
      "71": 64500,
      "72": 54900,
      "73": 6800,
      "74": 15300,
      "75": 45300,
      "81": 31700,
      "82": 10300,
      "83": 87200,
      "91": 35300,
      "92": 13900,
      "93": 53500,
      "94": 6100,
      "96": 29400,
      "02": 1600,
      "03": 2400
    },
    "earnings": {
      "10": 7.58,
      "11": 7.58,
      "12": 7.58,
      "13": 7.58,
      "14": 7.58,
      "15": 7.58,
      "16": 7.58,
      "17": 7.58,
      "18": 7.58,
      "19": 7.58,
      "20": 6.07,
      "21": 6.07,
      "22": 6.07,
      "23": 6.07,
      "24": 6.07,
      "25": 6.07,
      "26": 6.07,
      "27": 6.07,
      "28": 6.07,
      "29": 6.07,
      "30": 4.61,
      "31": 4.61,
      "32": 4.61,
      "33": 4.61,
      "34": 4.61,
      "35": 4.61,
      "36": 4.61,
      "37": 4.61,
      "38": 4.61,
      "39": 4.61,
      "40": 4.1,
      "41": 4.1,
      "42": 4.1,
      "43": 4.1,
      "44": 4.1,
      "45": 4.1,
      "46": 4.1,
      "47": 4.1,
      "48": 4.1,
      "49": 4.1,
      "50": 3.11,
      "51": 3.11,
      "52": 3.11,
      "53": 3.11,
      "54": 3.11,
      "55": 3.11,
      "56": 3.11,
      "57": 3.11,
      "58": 3.11,
      "59": 3.11,
      "70": 4.07,
      "71": 4.07,
      "72": 4.07,
      "73": 4.07,
      "74": 4.07,
      "75": 4.07,
      "76": 4.07,
      "77": 4.07,
      "78": 4.07,
      "79": 4.07,
      "80": 3.86,
      "81": 3.86,
      "82": 3.86,
      "83": 3.86,
      "84": 3.86,
      "85": 3.86,
      "86": 3.86,
      "87": 3.86,
      "88": 3.86,
      "89": 3.86,
      "90": 2.7,
      "91": 2.7,
      "92": 2.7,
      "93": 2.7,
      "94": 2.7,
      "95": 2.7,
      "96": 2.7,
      "97": 2.7,
      "98": 2.7,
      "99": 2.7
    }
  },
  "LU": {
    "employment": {
      "11": 2100,
      "12": 5000,
      "13": 2800,
      "14": 2200,
      "21": 15700,
      "22": 7400,
      "23": 18200,
      "24": 57200,
      "25": 16000,
      "26": 28300,
      "31": 4800,
      "32": 4200,
      "33": 28000,
      "34": 8700,
      "35": 3600,
      "41": 6300,
      "42": 4500,
      "43": 6300,
      "44": 2400,
      "51": 10300,
      "52": 7200,
      "53": 8000,
      "54": 4100,
      "61": 4000,
      "71": 5800,
      "72": 4800,
      "74": 2400,
      "81": 2400,
      "83": 9600,
      "91": 16000,
      "93": 3100
    },
    "earnings": {
      "10": 42.2,
      "11": 42.2,
      "12": 42.2,
      "13": 42.2,
      "14": 42.2,
      "15": 42.2,
      "16": 42.2,
      "17": 42.2,
      "18": 42.2,
      "19": 42.2,
      "20": 28.76,
      "21": 28.76,
      "22": 28.76,
      "23": 28.76,
      "24": 28.76,
      "25": 28.76,
      "26": 28.76,
      "27": 28.76,
      "28": 28.76,
      "29": 28.76,
      "30": 22.27,
      "31": 22.27,
      "32": 22.27,
      "33": 22.27,
      "34": 22.27,
      "35": 22.27,
      "36": 22.27,
      "37": 22.27,
      "38": 22.27,
      "39": 22.27,
      "40": 17.83,
      "41": 17.83,
      "42": 17.83,
      "43": 17.83,
      "44": 17.83,
      "45": 17.83,
      "46": 17.83,
      "47": 17.83,
      "48": 17.83,
      "49": 17.83,
      "50": 15.26,
      "51": 15.26,
      "52": 15.26,
      "53": 15.26,
      "54": 15.26,
      "55": 15.26,
      "56": 15.26,
      "57": 15.26,
      "58": 15.26,
      "59": 15.26,
      "60": 15.38,
      "61": 15.38,
      "62": 15.38,
      "63": 15.38,
      "64": 15.38,
      "65": 15.38,
      "66": 15.38,
      "67": 15.38,
      "68": 15.38,
      "69": 15.38,
      "70": 16.83,
      "71": 16.83,
      "72": 16.83,
      "73": 16.83,
      "74": 16.83,
      "75": 16.83,
      "76": 16.83,
      "77": 16.83,
      "78": 16.83,
      "79": 16.83,
      "80": 16.34,
      "81": 16.34,
      "82": 16.34,
      "83": 16.34,
      "84": 16.34,
      "85": 16.34,
      "86": 16.34,
      "87": 16.34,
      "88": 16.34,
      "89": 16.34,
      "90": 13.51,
      "91": 13.51,
      "92": 13.51,
      "93": 13.51,
      "94": 13.51,
      "95": 13.51,
      "96": 13.51,
      "97": 13.51,
      "98": 13.51,
      "99": 13.51
    }
  },
  "LV": {
    "employment": {
      "11": 36700,
      "12": 21800,
      "13": 21200,
      "14": 5700,
      "21": 23900,
      "22": 22600,
      "23": 40300,
      "24": 42500,
      "25": 23100,
      "26": 20300,
      "31": 23500,
      "32": 6600,
      "33": 62000,
      "34": 10000,
      "35": 6000,
      "41": 8000,
      "42": 14100,
      "43": 20900,
      "44": 2000,
      "51": 39000,
      "52": 47800,
      "53": 21900,
      "54": 11100,
      "61": 16100,
      "62": 5800,
      "63": 4100,
      "71": 30900,
      "72": 30100,
      "73": 2800,
      "74": 10100,
      "75": 20200,
      "81": 14300,
      "82": 4300,
      "83": 53400,
      "91": 19000,
      "92": 10200,
      "93": 50000,
      "94": 4900,
      "96": 16000,
      "02": 3300,
      "03": 3400
    },
    "earnings": {
      "10": 8.7,
      "11": 8.7,
      "12": 8.7,
      "13": 8.7,
      "14": 8.7,
      "15": 8.7,
      "16": 8.7,
      "17": 8.7,
      "18": 8.7,
      "19": 8.7,
      "20": 6.42,
      "21": 6.42,
      "22": 6.42,
      "23": 6.42,
      "24": 6.42,
      "25": 6.42,
      "26": 6.42,
      "27": 6.42,
      "28": 6.42,
      "29": 6.42,
      "30": 5.98,
      "31": 5.98,
      "32": 5.98,
      "33": 5.98,
      "34": 5.98,
      "35": 5.98,
      "36": 5.98,
      "37": 5.98,
      "38": 5.98,
      "39": 5.98,
      "40": 4.89,
      "41": 4.89,
      "42": 4.89,
      "43": 4.89,
      "44": 4.89,
      "45": 4.89,
      "46": 4.89,
      "47": 4.89,
      "48": 4.89,
      "49": 4.89,
      "50": 3.5,
      "51": 3.5,
      "52": 3.5,
      "53": 3.5,
      "54": 3.5,
      "55": 3.5,
      "56": 3.5,
      "57": 3.5,
      "58": 3.5,
      "59": 3.5,
      "60": 3.61,
      "61": 3.61,
      "62": 3.61,
      "63": 3.61,
      "64": 3.61,
      "65": 3.61,
      "66": 3.61,
      "67": 3.61,
      "68": 3.61,
      "69": 3.61,
      "70": 4.93,
      "71": 4.93,
      "72": 4.93,
      "73": 4.93,
      "74": 4.93,
      "75": 4.93,
      "76": 4.93,
      "77": 4.93,
      "78": 4.93,
      "79": 4.93,
      "80": 5,
      "81": 5,
      "82": 5,
      "83": 5,
      "84": 5,
      "85": 5,
      "86": 5,
      "87": 5,
      "88": 5,
      "89": 5,
      "90": 3.04,
      "91": 3.04,
      "92": 3.04,
      "93": 3.04,
      "94": 3.04,
      "95": 3.04,
      "96": 3.04,
      "97": 3.04,
      "98": 3.04,
      "99": 3.04
    }
  },
  "MT": {
    "employment": {
      "11": 7700,
      "12": 8600,
      "13": 6900,
      "14": 10200,
      "21": 8300,
      "22": 10100,
      "23": 12500,
      "24": 16100,
      "25": 7900,
      "26": 6200,
      "31": 6100,
      "32": 2500,
      "33": 18500,
      "34": 8900,
      "35": 2000,
      "41": 13000,
      "42": 9600,
      "43": 6300,
      "44": 1700,
      "51": 12400,
      "52": 19800,
      "53": 17400,
      "54": 6600,
      "61": 2100,
      "71": 14400,
      "72": 5200,
      "73": 1000,
      "74": 5100,
      "75": 4800,
      "81": 3800,
      "82": 4000,
      "83": 9200,
      "91": 10300,
      "93": 6200,
      "94": 2400,
      "96": 6500,
      "03": 1700
    },
    "earnings": {
      "10": 16.84,
      "11": 16.84,
      "12": 16.84,
      "13": 16.84,
      "14": 16.84,
      "15": 16.84,
      "16": 16.84,
      "17": 16.84,
      "18": 16.84,
      "19": 16.84,
      "20": 13.79,
      "21": 13.79,
      "22": 13.79,
      "23": 13.79,
      "24": 13.79,
      "25": 13.79,
      "26": 13.79,
      "27": 13.79,
      "28": 13.79,
      "29": 13.79,
      "30": 11.59,
      "31": 11.59,
      "32": 11.59,
      "33": 11.59,
      "34": 11.59,
      "35": 11.59,
      "36": 11.59,
      "37": 11.59,
      "38": 11.59,
      "39": 11.59,
      "40": 9.01,
      "41": 9.01,
      "42": 9.01,
      "43": 9.01,
      "44": 9.01,
      "45": 9.01,
      "46": 9.01,
      "47": 9.01,
      "48": 9.01,
      "49": 9.01,
      "50": 8.07,
      "51": 8.07,
      "52": 8.07,
      "53": 8.07,
      "54": 8.07,
      "55": 8.07,
      "56": 8.07,
      "57": 8.07,
      "58": 8.07,
      "59": 8.07,
      "60": 8.09,
      "61": 8.09,
      "62": 8.09,
      "63": 8.09,
      "64": 8.09,
      "65": 8.09,
      "66": 8.09,
      "67": 8.09,
      "68": 8.09,
      "69": 8.09,
      "70": 10.06,
      "71": 10.06,
      "72": 10.06,
      "73": 10.06,
      "74": 10.06,
      "75": 10.06,
      "76": 10.06,
      "77": 10.06,
      "78": 10.06,
      "79": 10.06,
      "80": 9.4,
      "81": 9.4,
      "82": 9.4,
      "83": 9.4,
      "84": 9.4,
      "85": 9.4,
      "86": 9.4,
      "87": 9.4,
      "88": 9.4,
      "89": 9.4,
      "90": 7.06,
      "91": 7.06,
      "92": 7.06,
      "93": 7.06,
      "94": 7.06,
      "95": 7.06,
      "96": 7.06,
      "97": 7.06,
      "98": 7.06,
      "99": 7.06
    }
  },
  "NL": {
    "employment": {
      "11": 60600,
      "12": 149200,
      "13": 213900,
      "14": 97400,
      "21": 361200,
      "22": 385200,
      "23": 465300,
      "24": 864900,
      "25": 452900,
      "26": 389400,
      "31": 250200,
      "32": 270100,
      "33": 644800,
      "34": 361500,
      "35": 81600,
      "41": 145600,
      "42": 191800,
      "43": 368200,
      "44": 101000,
      "51": 442700,
      "52": 630600,
      "53": 440100,
      "54": 94400,
      "61": 127800,
      "62": 2200,
      "71": 234700,
      "72": 157300,
      "73": 27000,
      "74": 86100,
      "75": 76200,
      "81": 75200,
      "82": 23800,
      "83": 242500,
      "91": 210000,
      "92": 32299,
      "93": 359400,
      "94": 77500,
      "96": 37600,
      "01": 8200,
      "02": 9000,
      "03": 9800
    },
    "earnings": {
      "10": 31.82,
      "11": 31.82,
      "12": 31.82,
      "13": 31.82,
      "14": 31.82,
      "15": 31.82,
      "16": 31.82,
      "17": 31.82,
      "18": 31.82,
      "19": 31.82,
      "20": 24.47,
      "21": 24.47,
      "22": 24.47,
      "23": 24.47,
      "24": 24.47,
      "25": 24.47,
      "26": 24.47,
      "27": 24.47,
      "28": 24.47,
      "29": 24.47,
      "30": 20.37,
      "31": 20.37,
      "32": 20.37,
      "33": 20.37,
      "34": 20.37,
      "35": 20.37,
      "36": 20.37,
      "37": 20.37,
      "38": 20.37,
      "39": 20.37,
      "40": 16.98,
      "41": 16.98,
      "42": 16.98,
      "43": 16.98,
      "44": 16.98,
      "45": 16.98,
      "46": 16.98,
      "47": 16.98,
      "48": 16.98,
      "49": 16.98,
      "50": 14.24,
      "51": 14.24,
      "52": 14.24,
      "53": 14.24,
      "54": 14.24,
      "55": 14.24,
      "56": 14.24,
      "57": 14.24,
      "58": 14.24,
      "59": 14.24,
      "60": 12.85,
      "61": 12.85,
      "62": 12.85,
      "63": 12.85,
      "64": 12.85,
      "65": 12.85,
      "66": 12.85,
      "67": 12.85,
      "68": 12.85,
      "69": 12.85,
      "70": 16.73,
      "71": 16.73,
      "72": 16.73,
      "73": 16.73,
      "74": 16.73,
      "75": 16.73,
      "76": 16.73,
      "77": 16.73,
      "78": 16.73,
      "79": 16.73,
      "80": 15.89,
      "81": 15.89,
      "82": 15.89,
      "83": 15.89,
      "84": 15.89,
      "85": 15.89,
      "86": 15.89,
      "87": 15.89,
      "88": 15.89,
      "89": 15.89,
      "90": 12.6,
      "91": 12.6,
      "92": 12.6,
      "93": 12.6,
      "94": 12.6,
      "95": 12.6,
      "96": 12.6,
      "97": 12.6,
      "98": 12.6,
      "99": 12.6,
      "00": 17.17,
      "01": 17.17,
      "02": 17.17,
      "03": 17.17,
      "04": 17.17,
      "05": 17.17,
      "06": 17.17,
      "07": 17.17,
      "08": 17.17,
      "09": 17.17
    }
  },
  "PL": {
    "employment": {
      "11": 214700,
      "12": 325600,
      "13": 342200,
      "14": 269800,
      "21": 572700,
      "22": 567800,
      "23": 875500,
      "24": 1079100,
      "25": 436800,
      "26": 386100,
      "31": 614700,
      "32": 221700,
      "33": 1109900,
      "34": 233400,
      "35": 110500,
      "41": 542900,
      "42": 154500,
      "43": 488900,
      "44": 86900,
      "51": 506700,
      "52": 1198500,
      "53": 200000,
      "54": 231900,
      "61": 1150200,
      "62": 15900,
      "71": 913700,
      "72": 711400,
      "73": 68400,
      "74": 255200,
      "75": 468100,
      "81": 450600,
      "82": 136500,
      "83": 929500,
      "91": 325300,
      "92": 44500,
      "93": 202900,
      "94": 74900,
      "96": 95500,
      "01": 27000,
      "02": 39700,
      "03": 66100
    },
    "earnings": {
      "10": 8.41,
      "11": 8.41,
      "12": 8.41,
      "13": 8.41,
      "14": 8.41,
      "15": 8.41,
      "16": 8.41,
      "17": 8.41,
      "18": 8.41,
      "19": 8.41,
      "20": 7.8,
      "21": 7.8,
      "22": 7.8,
      "23": 7.8,
      "24": 7.8,
      "25": 7.8,
      "26": 7.8,
      "27": 7.8,
      "28": 7.8,
      "29": 7.8,
      "30": 5.31,
      "31": 5.31,
      "32": 5.31,
      "33": 5.31,
      "34": 5.31,
      "35": 5.31,
      "36": 5.31,
      "37": 5.31,
      "38": 5.31,
      "39": 5.31,
      "40": 4.46,
      "41": 4.46,
      "42": 4.46,
      "43": 4.46,
      "44": 4.46,
      "45": 4.46,
      "46": 4.46,
      "47": 4.46,
      "48": 4.46,
      "49": 4.46,
      "50": 3.32,
      "51": 3.32,
      "52": 3.32,
      "53": 3.32,
      "54": 3.32,
      "55": 3.32,
      "56": 3.32,
      "57": 3.32,
      "58": 3.32,
      "59": 3.32,
      "60": 3.48,
      "61": 3.48,
      "62": 3.48,
      "63": 3.48,
      "64": 3.48,
      "65": 3.48,
      "66": 3.48,
      "67": 3.48,
      "68": 3.48,
      "69": 3.48,
      "70": 4.48,
      "71": 4.48,
      "72": 4.48,
      "73": 4.48,
      "74": 4.48,
      "75": 4.48,
      "76": 4.48,
      "77": 4.48,
      "78": 4.48,
      "79": 4.48,
      "80": 4.44,
      "81": 4.44,
      "82": 4.44,
      "83": 4.44,
      "84": 4.44,
      "85": 4.44,
      "86": 4.44,
      "87": 4.44,
      "88": 4.44,
      "89": 4.44,
      "90": 3.25,
      "91": 3.25,
      "92": 3.25,
      "93": 3.25,
      "94": 3.25,
      "95": 3.25,
      "96": 3.25,
      "97": 3.25,
      "98": 3.25,
      "99": 3.25
    }
  },
  "PT": {
    "employment": {
      "11": 30600,
      "12": 49600,
      "13": 91500,
      "14": 95000,
      "21": 182500,
      "22": 190500,
      "23": 243500,
      "24": 191900,
      "25": 131500,
      "26": 134200,
      "31": 111400,
      "32": 63800,
      "33": 257600,
      "34": 61300,
      "35": 40700,
      "41": 253200,
      "42": 106500,
      "43": 91500,
      "44": 14300,
      "51": 219700,
      "52": 354400,
      "53": 229200,
      "54": 107500,
      "61": 78500,
      "62": 17100,
      "71": 214300,
      "72": 172700,
      "73": 28500,
      "74": 75200,
      "75": 141500,
      "81": 176800,
      "82": 24800,
      "83": 209500,
      "91": 188000,
      "92": 16500,
      "93": 96800,
      "94": 45800,
      "96": 61800,
      "01": 4900,
      "02": 7300,
      "03": 7600
    },
    "earnings": {
      "10": 16.76,
      "11": 16.76,
      "12": 16.76,
      "13": 16.76,
      "14": 16.76,
      "15": 16.76,
      "16": 16.76,
      "17": 16.76,
      "18": 16.76,
      "19": 16.76,
      "20": 11.9,
      "21": 11.9,
      "22": 11.9,
      "23": 11.9,
      "24": 11.9,
      "25": 11.9,
      "26": 11.9,
      "27": 11.9,
      "28": 11.9,
      "29": 11.9,
      "30": 7.61,
      "31": 7.61,
      "32": 7.61,
      "33": 7.61,
      "34": 7.61,
      "35": 7.61,
      "36": 7.61,
      "37": 7.61,
      "38": 7.61,
      "39": 7.61,
      "40": 5.5,
      "41": 5.5,
      "42": 5.5,
      "43": 5.5,
      "44": 5.5,
      "45": 5.5,
      "46": 5.5,
      "47": 5.5,
      "48": 5.5,
      "49": 5.5,
      "50": 4.61,
      "51": 4.61,
      "52": 4.61,
      "53": 4.61,
      "54": 4.61,
      "55": 4.61,
      "56": 4.61,
      "57": 4.61,
      "58": 4.61,
      "59": 4.61,
      "60": 4.27,
      "61": 4.27,
      "62": 4.27,
      "63": 4.27,
      "64": 4.27,
      "65": 4.27,
      "66": 4.27,
      "67": 4.27,
      "68": 4.27,
      "69": 4.27,
      "70": 4.81,
      "71": 4.81,
      "72": 4.81,
      "73": 4.81,
      "74": 4.81,
      "75": 4.81,
      "76": 4.81,
      "77": 4.81,
      "78": 4.81,
      "79": 4.81,
      "80": 4.79,
      "81": 4.79,
      "82": 4.79,
      "83": 4.79,
      "84": 4.79,
      "85": 4.79,
      "86": 4.79,
      "87": 4.79,
      "88": 4.79,
      "89": 4.79,
      "90": 4.22,
      "91": 4.22,
      "92": 4.22,
      "93": 4.22,
      "94": 4.22,
      "95": 4.22,
      "96": 4.22,
      "97": 4.22,
      "98": 4.22,
      "99": 4.22
    }
  },
  "RO": {
    "employment": {
      "11": 73600,
      "12": 36700,
      "13": 62600,
      "14": 32800,
      "21": 264400,
      "22": 217800,
      "23": 263100,
      "24": 351900,
      "25": 94900,
      "26": 148800,
      "31": 99000,
      "32": 109300,
      "33": 243900,
      "34": 35900,
      "35": 47400,
      "41": 133300,
      "42": 59400,
      "43": 130900,
      "44": 35200,
      "51": 265900,
      "52": 727800,
      "53": 120900,
      "54": 207200,
      "61": 594200,
      "62": 7900,
      "71": 454400,
      "72": 435400,
      "73": 22200,
      "74": 149600,
      "75": 294500,
      "81": 282700,
      "82": 142700,
      "83": 632100,
      "91": 134300,
      "92": 155500,
      "93": 358100,
      "94": 12500,
      "96": 124800,
      "01": 19600,
      "02": 13100,
      "03": 14800
    },
    "earnings": {
      "10": 7.97,
      "11": 7.97,
      "12": 7.97,
      "13": 7.97,
      "14": 7.97,
      "15": 7.97,
      "16": 7.97,
      "17": 7.97,
      "18": 7.97,
      "19": 7.97,
      "20": 6.73,
      "21": 6.73,
      "22": 6.73,
      "23": 6.73,
      "24": 6.73,
      "25": 6.73,
      "26": 6.73,
      "27": 6.73,
      "28": 6.73,
      "29": 6.73,
      "30": 4.65,
      "31": 4.65,
      "32": 4.65,
      "33": 4.65,
      "34": 4.65,
      "35": 4.65,
      "36": 4.65,
      "37": 4.65,
      "38": 4.65,
      "39": 4.65,
      "40": 3.67,
      "41": 3.67,
      "42": 3.67,
      "43": 3.67,
      "44": 3.67,
      "45": 3.67,
      "46": 3.67,
      "47": 3.67,
      "48": 3.67,
      "49": 3.67,
      "50": 2.71,
      "51": 2.71,
      "52": 2.71,
      "53": 2.71,
      "54": 2.71,
      "55": 2.71,
      "56": 2.71,
      "57": 2.71,
      "58": 2.71,
      "59": 2.71,
      "60": 2.84,
      "61": 2.84,
      "62": 2.84,
      "63": 2.84,
      "64": 2.84,
      "65": 2.84,
      "66": 2.84,
      "67": 2.84,
      "68": 2.84,
      "69": 2.84,
      "70": 3.55,
      "71": 3.55,
      "72": 3.55,
      "73": 3.55,
      "74": 3.55,
      "75": 3.55,
      "76": 3.55,
      "77": 3.55,
      "78": 3.55,
      "79": 3.55,
      "80": 3.28,
      "81": 3.28,
      "82": 3.28,
      "83": 3.28,
      "84": 3.28,
      "85": 3.28,
      "86": 3.28,
      "87": 3.28,
      "88": 3.28,
      "89": 3.28,
      "90": 2.66,
      "91": 2.66,
      "92": 2.66,
      "93": 2.66,
      "94": 2.66,
      "95": 2.66,
      "96": 2.66,
      "97": 2.66,
      "98": 2.66,
      "99": 2.66
    }
  },
  "SE": {
    "employment": {
      "11": 12600,
      "12": 122600,
      "13": 151300,
      "14": 37500,
      "21": 200900,
      "22": 253700,
      "23": 345000,
      "24": 384900,
      "25": 288900,
      "26": 222700,
      "31": 260700,
      "32": 62900,
      "33": 445200,
      "34": 93500,
      "35": 62000,
      "41": 46900,
      "42": 61700,
      "43": 172700,
      "44": 26600,
      "51": 171600,
      "52": 213400,
      "53": 408800,
      "54": 45000,
      "61": 50400,
      "62": 9800,
      "71": 172100,
      "72": 123400,
      "73": 14800,
      "74": 70900,
      "75": 28800,
      "81": 57800,
      "82": 39500,
      "83": 168700,
      "91": 69300,
      "92": 3700,
      "93": 50200,
      "94": 66400,
      "96": 19600,
      "01": 12100,
      "03": 5300
    },
    "earnings": {
      "10": 29.55,
      "11": 29.55,
      "12": 29.55,
      "13": 29.55,
      "14": 29.55,
      "15": 29.55,
      "16": 29.55,
      "17": 29.55,
      "18": 29.55,
      "19": 29.55,
      "20": 21.56,
      "21": 21.56,
      "22": 21.56,
      "23": 21.56,
      "24": 21.56,
      "25": 21.56,
      "26": 21.56,
      "27": 21.56,
      "28": 21.56,
      "29": 21.56,
      "30": 20.25,
      "31": 20.25,
      "32": 20.25,
      "33": 20.25,
      "34": 20.25,
      "35": 20.25,
      "36": 20.25,
      "37": 20.25,
      "38": 20.25,
      "39": 20.25,
      "40": 16.42,
      "41": 16.42,
      "42": 16.42,
      "43": 16.42,
      "44": 16.42,
      "45": 16.42,
      "46": 16.42,
      "47": 16.42,
      "48": 16.42,
      "49": 16.42,
      "50": 15.97,
      "51": 15.97,
      "52": 15.97,
      "53": 15.97,
      "54": 15.97,
      "55": 15.97,
      "56": 15.97,
      "57": 15.97,
      "58": 15.97,
      "59": 15.97,
      "60": 15.22,
      "61": 15.22,
      "62": 15.22,
      "63": 15.22,
      "64": 15.22,
      "65": 15.22,
      "66": 15.22,
      "67": 15.22,
      "68": 15.22,
      "69": 15.22,
      "70": 18.93,
      "71": 18.93,
      "72": 18.93,
      "73": 18.93,
      "74": 18.93,
      "75": 18.93,
      "76": 18.93,
      "77": 18.93,
      "78": 18.93,
      "79": 18.93,
      "80": 17.51,
      "81": 17.51,
      "82": 17.51,
      "83": 17.51,
      "84": 17.51,
      "85": 17.51,
      "86": 17.51,
      "87": 17.51,
      "88": 17.51,
      "89": 17.51,
      "90": 14.27,
      "91": 14.27,
      "92": 14.27,
      "93": 14.27,
      "94": 14.27,
      "95": 14.27,
      "96": 14.27,
      "97": 14.27,
      "98": 14.27,
      "99": 14.27
    }
  },
  "SI": {
    "employment": {
      "11": 3300,
      "12": 11400,
      "13": 15300,
      "14": 6100,
      "21": 43900,
      "22": 31700,
      "23": 57700,
      "24": 35800,
      "25": 19300,
      "26": 33200,
      "31": 35800,
      "32": 18400,
      "33": 70300,
      "34": 9300,
      "35": 7000,
      "41": 26700,
      "42": 12700,
      "43": 27800,
      "44": 7400,
      "51": 46800,
      "52": 55900,
      "53": 18600,
      "54": 13400,
      "61": 23500,
      "62": 2800,
      "71": 35400,
      "72": 51700,
      "73": 6500,
      "74": 14200,
      "75": 25300,
      "81": 31100,
      "82": 14100,
      "83": 39900,
      "91": 26800,
      "92": 6000,
      "93": 46200,
      "94": 9300,
      "96": 16100,
      "01": 1600,
      "02": 2300,
      "03": 3000
    },
    "earnings": {
      "10": 17.04,
      "11": 17.04,
      "12": 17.04,
      "13": 17.04,
      "14": 17.04,
      "15": 17.04,
      "16": 17.04,
      "17": 17.04,
      "18": 17.04,
      "19": 17.04,
      "20": 11.98,
      "21": 11.98,
      "22": 11.98,
      "23": 11.98,
      "24": 11.98,
      "25": 11.98,
      "26": 11.98,
      "27": 11.98,
      "28": 11.98,
      "29": 11.98,
      "30": 9.66,
      "31": 9.66,
      "32": 9.66,
      "33": 9.66,
      "34": 9.66,
      "35": 9.66,
      "36": 9.66,
      "37": 9.66,
      "38": 9.66,
      "39": 9.66,
      "40": 7.94,
      "41": 7.94,
      "42": 7.94,
      "43": 7.94,
      "44": 7.94,
      "45": 7.94,
      "46": 7.94,
      "47": 7.94,
      "48": 7.94,
      "49": 7.94,
      "50": 6.13,
      "51": 6.13,
      "52": 6.13,
      "53": 6.13,
      "54": 6.13,
      "55": 6.13,
      "56": 6.13,
      "57": 6.13,
      "58": 6.13,
      "59": 6.13,
      "60": 6.58,
      "61": 6.58,
      "62": 6.58,
      "63": 6.58,
      "64": 6.58,
      "65": 6.58,
      "66": 6.58,
      "67": 6.58,
      "68": 6.58,
      "69": 6.58,
      "70": 7.34,
      "71": 7.34,
      "72": 7.34,
      "73": 7.34,
      "74": 7.34,
      "75": 7.34,
      "76": 7.34,
      "77": 7.34,
      "78": 7.34,
      "79": 7.34,
      "80": 6.75,
      "81": 6.75,
      "82": 6.75,
      "83": 6.75,
      "84": 6.75,
      "85": 6.75,
      "86": 6.75,
      "87": 6.75,
      "88": 6.75,
      "89": 6.75,
      "90": 5.62,
      "91": 5.62,
      "92": 5.62,
      "93": 5.62,
      "94": 5.62,
      "95": 5.62,
      "96": 5.62,
      "97": 5.62,
      "98": 5.62,
      "99": 5.62,
      "00": 7.94,
      "01": 7.94,
      "02": 7.94,
      "03": 7.94,
      "04": 7.94,
      "05": 7.94,
      "06": 7.94,
      "07": 7.94,
      "08": 7.94,
      "09": 7.94
    }
  },
  "SK": {
    "employment": {
      "11": 16300,
      "12": 36100,
      "13": 56000,
      "14": 38700,
      "21": 55500,
      "22": 42200,
      "23": 129600,
      "24": 84700,
      "25": 57100,
      "26": 57900,
      "31": 126200,
      "32": 79500,
      "33": 150700,
      "34": 18700,
      "35": 24400,
      "41": 84800,
      "42": 31800,
      "43": 116300,
      "44": 16400,
      "51": 132800,
      "52": 194000,
      "53": 70600,
      "54": 44400,
      "61": 13300,
      "62": 8900,
      "71": 115500,
      "72": 124200,
      "73": 11100,
      "74": 50100,
      "75": 70300,
      "81": 99500,
      "82": 83100,
      "83": 133200,
      "91": 47000,
      "92": 6900,
      "93": 65400,
      "94": 17100,
      "96": 18100,
      "03": 8800
    },
    "earnings": {
      "10": 10.12,
      "11": 10.12,
      "12": 10.12,
      "13": 10.12,
      "14": 10.12,
      "15": 10.12,
      "16": 10.12,
      "17": 10.12,
      "18": 10.12,
      "19": 10.12,
      "20": 7.22,
      "21": 7.22,
      "22": 7.22,
      "23": 7.22,
      "24": 7.22,
      "25": 7.22,
      "26": 7.22,
      "27": 7.22,
      "28": 7.22,
      "29": 7.22,
      "30": 6.55,
      "31": 6.55,
      "32": 6.55,
      "33": 6.55,
      "34": 6.55,
      "35": 6.55,
      "36": 6.55,
      "37": 6.55,
      "38": 6.55,
      "39": 6.55,
      "40": 5.23,
      "41": 5.23,
      "42": 5.23,
      "43": 5.23,
      "44": 5.23,
      "45": 5.23,
      "46": 5.23,
      "47": 5.23,
      "48": 5.23,
      "49": 5.23,
      "50": 4.39,
      "51": 4.39,
      "52": 4.39,
      "53": 4.39,
      "54": 4.39,
      "55": 4.39,
      "56": 4.39,
      "57": 4.39,
      "58": 4.39,
      "59": 4.39,
      "60": 3.87,
      "61": 3.87,
      "62": 3.87,
      "63": 3.87,
      "64": 3.87,
      "65": 3.87,
      "66": 3.87,
      "67": 3.87,
      "68": 3.87,
      "69": 3.87,
      "70": 5.83,
      "71": 5.83,
      "72": 5.83,
      "73": 5.83,
      "74": 5.83,
      "75": 5.83,
      "76": 5.83,
      "77": 5.83,
      "78": 5.83,
      "79": 5.83,
      "80": 5.4,
      "81": 5.4,
      "82": 5.4,
      "83": 5.4,
      "84": 5.4,
      "85": 5.4,
      "86": 5.4,
      "87": 5.4,
      "88": 5.4,
      "89": 5.4,
      "90": 3.8,
      "91": 3.8,
      "92": 3.8,
      "93": 3.8,
      "94": 3.8,
      "95": 3.8,
      "96": 3.8,
      "97": 3.8,
      "98": 3.8,
      "99": 3.8
    }
  }
}