{
  "className": "Concept",
  "classId": "http://www.w3.org/2004/02/skos/core#Concept",
  "uri": "http://data.europa.eu/esco/isco/C5242",
  "title": "Sales demonstrators",
  "preferredLabel": {
    "de": "Produktvorführer",
    "no": "Demonstrasjonsselgere",
    "fi": "Tuote-esittelijät",
    "sv": "Butiksdemonstratörer m.fl.",
    "pt": "Demonstradores em lojas",
    "bg": "Демонстратори",
    "mt": "Dimostraturi tal-bejgħ",
    "el": "Υπάλληλοι επίδειξης προϊόντων",
    "lt": "Prekių demonstruotojai",
    "en": "Sales demonstrators",
    "hr": "Demonstratori/demonstratorice za prodaju",
    "lv": "Preču demonstrētāji",
    "it": "Dimostratori",
    "fr": "Démonstrateurs en magasin",
    "hu": "Termékbemutató ügynökök",
    "es": "Demostradores de tiendas",
    "et": "Tootetutvustajad",
    "cs": "Předváděči zboží",
    "sk": "Predvádzači tovaru",
    "sl": "Demonstratorji/demonstratorke za prodajo",
    "pl": "Demonstratorzy wyrobów",
    "da": "Demonstrationsarbejde",
    "ro": "Prezentatori produse",
    "nl": "Demonstrateurs"
  },
  "code": "5242",
  "codes": [
    {
      "datatype": "",
      "value": "5242"
    },
    {
      "datatype": "http://data.europa.eu/esco/Notation/ISCO08",
      "value": "5242"
    }
  ],
  "description": {
    "en": {
      "literal": "Sales demonstrators demonstrate goods at commercial premises, exhibitions and private homes.\nTasks include -\n(a)  setting up displays and demonstrating articles for sale to inform customers about their characteristics and mode of use, as well as to stimulate buying interest;\n(b)  answering questions and offering advice on the use of goods;\n(c)  selling goods or directing customers to sales staff;\n(d)  taking orders and making arrangements for payment, delivery and collection of goods;\n(e)  offering sample goods and distributing catalogues and advertising material.\nExamples of the occupations classified here:\n- Demonstrator\n- Sales merchandiser\nSome related occupations classified elsewhere:\n- Market salesperson - 5211\n- Street stall salesperson - 5211\n- Door-to-door salesperson - 5243\n",
      "mimetype": "plain/text"
    }
  },
  "_links": {
    "self": {
      "href": "https://ec.europa.eu/esco/api/resource/concept?uri=http://data.europa.eu/esco/isco/C5242&language=en",
      "uri": "http://data.europa.eu/esco/isco/C5242",
      "title": "Sales demonstrators"
    },
    "isInScheme": [
      {
        "href": "https://ec.europa.eu/esco/api/resource/taxonomy?uri=http://data.europa.eu/esco/concept-scheme/isco&language=en",
        "uri": "http://data.europa.eu/esco/concept-scheme/isco",
        "title": "ISCO 2008"
      },
      {
        "href": "https://ec.europa.eu/esco/api/resource/taxonomy?uri=http://data.europa.eu/esco/concept-scheme/occupations&language=en",
        "uri": "http://data.europa.eu/esco/concept-scheme/occupations",
        "title": "ESCO Occupations"
      }
    ],
    "broaderConcept": [
      {
        "href": "https://ec.europa.eu/esco/api/resource/concept?uri=http://data.europa.eu/esco/isco/C524&language=en",
        "uri": "http://data.europa.eu/esco/isco/C524",
        "title": "Other sales workers",
        "code": "524"
      }
    ],
    "narrowerOccupation": [
      {
        "href": "https://ec.europa.eu/esco/api/resource/occupation?uri=http://data.europa.eu/esco/occupation/056f1849-7ff8-4d6f-9b8a-176a610bba44&language=en",
        "uri": "http://data.europa.eu/esco/occupation/056f1849-7ff8-4d6f-9b8a-176a610bba44",
        "title": "promotions demonstrator"
      }
    ]
  },
  "_embedded": {}
}